HW3/counter.v
module counter (input clock, input [7:0] in, input latch, input dec, input divide_by_two, output zero);
  reg [7:0] value;
  assign zero = value == 8'b0;
  always @(posedge clock) begin
    if (latch) value <= in;
    else if (!zero && dec) value <= value - 1'b1;
    else if (!zero && divide_by_two) value <= {1'b0, value[7:1]};
  end
endmodule

HW3/divide_by_two_tb.v
`include "counter.v"

module divide_by_two_tb;

  reg clock100;
  reg latch, dec, divide_by_two;
  reg [7:0] in;
  wire zero;
  //following block executed only once
  initial begin
    // below commands save waves as vcd files. These are
    // not needed if Modelsim used as the simulator. This
    // useful if cadence tools are used for simulation.
    $dumpfile("count.vcd");  // waveforms in this file
    $dumpvars;  // saves all waveforms
    clock100 = 0;
    latch = 0;
    dec = 0;
    divide_by_two = 0;
    in = 8'b00001000;
    #16 latch = 1;  // wait 16 ns
    #10 latch = 0;  // wait 10 ns
    #10 dec = 1;
    #20 dec = 0;
    in = 8'b00100000;
    divide_by_two = 1;

    #40 latch = 1;
    #10 latch = 0;

    #100 $finish;  //finished with simulation
  end
  always #5 clock100 = ~clock100;  // 10ns clock
  // instantiate modules -- call this counter u1
  counter dut (
      .clock(clock100),
      .in(in),
      .latch(latch),
      .dec(dec),
      .divide_by_two(divide_by_two),
      .zero(zero)
  );

endmodule

HW3/count.vcd
$date
	Wed Sep 13 16:29:39 2023
$end
$version
	ModelSim Version 2021.2
$end
$timescale
	1ns
$end

$scope module divide_by_two_tb $end
$var reg 1 ! clock100 $end
$var reg 1 " latch $end
$var reg 1 # dec $end
$var reg 1 $ divide_by_two $end
$var reg 8 % in [7:0] $end
$var wire 1 & zero $end

$scope module dut $end
$var wire 1 ' clock $end
$var wire 1 ( in [7] $end
$var wire 1 ) in [6] $end
$var wire 1 * in [5] $end
$var wire 1 + in [4] $end
$var wire 1 , in [3] $end
$var wire 1 - in [2] $end
$var wire 1 . in [1] $end
$var wire 1 / in [0] $end
$var wire 1 0 latch $end
$var wire 1 1 dec $end
$var wire 1 2 divide_by_two $end
$var wire 1 & zero $end
$var reg 8 3 value [7:0] $end
$upscope $end
$upscope $end
$enddefinitions $end
#0
$dumpvars
0!
0"
0#
0$
b1000 %
bx 3
x&
02
01
00
0/
0.
0-
1,
0+
0*
0)
0(
0'
$end
#5
1!
1'
#10
0!
0'
#15
1!
1'
#16
1"
10
#20
0!
0'
#25
1!
1'
b1000 3
0&
#26
0"
00
#30
0!
0'
#35
1!
1'
#36
1#
11
#40
0!
0'
#45
1!
1'
b111 3
#50
0!
0'
#55
1!
1'
b110 3
#56
0#
b100000 %
1$
01
0,
1*
12
#60
0!
0'
#65
1!
1'
b11 3
#70
0!
0'
#75
1!
1'
b1 3
#80
0!
0'
#85
1!
1'
b0 3
1&
#90
0!
0'
#95
1!
1'
#96
1"
10
#100
0!
0'
#105
1!
1'
b100000 3
0&
#106
0"
00
#110
0!
0'
#115
1!
1'
b10000 3
#120
0!
0'
#125
1!
1'
b1000 3
#130
0!
0'
#135
1!
1'
b100 3
#140
0!
0'
#145
1!
1'
b10 3
#150
0!
0'
#155
1!
1'
b1 3
#160
0!
0'
#165
1!
1'
b0 3
1&
